{
	"display":
	{
		"icon": {"item": "minecraft:pumpkin"},
		"title": {"text": "Not so spooky anymore"},
		"description": {"text": "Seriously: Jack'o'lanterns are SO HARD to make now. Why mojang? Why? Also you collected a stack of pumpkins. Well done you."},
		"frame": "task",
		"show_toast": true,
		"announce_to_chat": true,
		"hidden": false
	},
	"parent": "crutech:joh/master_farmer",
	"criteria":
	{
		"64_pumpkins":
		{
			"trigger": "minecraft:inventory_changed",
			"conditions": 
			{
				"items": 
				[
					{
						"item": "minecraft:pumpkin",
						"count": 64
					}
				]
			}
		}
	},
	"requirements":
	[
		[
			"64_pumpkins"
		]
	]
}

